Workbook

Sheet Calculadora
B2: Calculadora de Preço — Mercado Livre
B3: Preencha só as células amarelas. O resto é automático.
B5: ① Preencha | E5: ② Dados puxados da base
B6: Tipo de produto | C6: Eletrônicos, Áudio e Vídeo | E6: Tarifa ML | F6: =IFERROR(INDEX('Base de Produtos'!$B$6:$H$36,MATCH($C$6,'Base de Produtos'!$B$6:$B$36,0),IF($C$11="Premium",3,2)),0) -> 0.13
B7: Origem | C7: Nacional | E7: Imposto sobre a venda | F7: =IFERROR(INDEX('Base de Produtos'!$B$6:$H$36,MATCH($C$6,'Base de Produtos'!$B$6:$B$36,0),4),0) -> 0.06
B8: Valor de compra (R$ por unidade) | C8: 45 | E8: Imposto de importação | F8: =IF($C$7="Internacional",IFERROR(INDEX('Base de Produtos'!$B$6:$H$36,MATCH($C$6,'Base de Produtos'!$B$6:$B$36,0),5),0),0) -> 0
B9: Frete da compra (R$ por unidade) | C9: 5 | E9: ICMS importação | F9: =IF($C$7="Internacional",IFERROR(INDEX('Base de Produtos'!$B$6:$H$36,MATCH($C$6,'Base de Produtos'!$B$6:$B$36,0),6),0),0) -> 0
B10: Lucro desejado | C10: 0.2 | E10: Embalagem | F10: =IFERROR(INDEX('Base de Produtos'!$B$6:$H$36,MATCH($C$6,'Base de Produtos'!$B$6:$B$36,0),7),0) -> 2
B11: Tipo de anúncio | C11: Clássico | E11: Mercado Ads + devoluções | F11: ='Base de Produtos'!$K$6+'Base de Produtos'!$K$7 -> 0.02
B12: Frete de envio ao cliente (R$) — opcional | C12: 0 | E12: =IF(ISNA(MATCH($C$6,'Base de Produtos'!$B$6:$B$36,0)),"⚠ Tipo de produto não encontrado na base","")
B13: Envio ao cliente: valor do Simulador de Custos do ML para o seu produto. Deixe 0 se o comprador paga.
B15: ③ Custo do produto | E15: ⑤ Compare: preço para cada % de lucro
B16: Compra + frete | C16: =$C$8+$C$9 -> 50 | E16: Lucro | F16: Preço Clássico | G16: Lucro R$ | H16: Preço Premium | I16: Lucro R$
B17: Impostos de importação | C17: =IF($C$7="Internacional",($C$8+$C$9)*(1+$F$8)/(1-$F$9)-($C$8+$C$9),0) -> 0 | E17: ='Base de Produtos'!J11 -> 0.05 | F17: =IF(OR($C$8="",$E17=""),"",IF((1-IFERROR(INDEX('Base de Produtos'!$B$6:$H$36,MATCH($C$6,'Base de Produtos'!$B$6:$B$36,0),2),0)-$F$7-$F$11-$E17)<=0,"—",CEILING($C$19/(1-IFERROR(INDEX('Base de Produtos'!$B$6:$H$36,MATCH($C$6,'Base de Produtos'!$B$6:$B$36,0),2),0)-$F$7-$F$11-$E17)+0.1,1)-0.1)) -> 70.9 | G17: =IF(ISNUMBER(F17),F17*(1-IFERROR(INDEX('Base de Produtos'!$B$6:$H$36,MATCH($C$6,'Base de Produtos'!$B$6:$B$36,0),2),0)-$F$7-$F$11)-$C$19,"") -> 4.011 | H17: =IF(OR($C$8="",$E17=""),"",IF((1-IFERROR(INDEX('Base de Produtos'!$B$6:$H$36,MATCH($C$6,'Base de Produtos'!$B$6:$B$36,0),3),0)-$F$7-$F$11-$E17)<=0,"—",CEILING($C$19/(1-IFERROR(INDEX('Base de Produtos'!$B$6:$H$36,MATCH($C$6,'Base de Produtos'!$B$6:$B$36,0),3),0)-$F$7-$F$11-$E17)+0.1,1)-0.1)) -> 75.9 | I17: =IF(ISNUMBER(H17),H17*(1-IFERROR(INDEX('Base de Produtos'!$B$6:$H$36,MATCH($C$6,'Base de Produtos'!$B$6:$B$36,0),3),0)-$F$7-$F$11)-$C$19,"") -> 4.166
B18: Embalagem + envio ao cliente | C18: =$F$10+$C$12 -> 2 | E18: ='Base de Produtos'!J12 -> 0.1 | F18: =IF(OR($C$8="",$E18=""),"",IF((1-IFERROR(INDEX('Base de Produtos'!$B$6:$H$36,MATCH($C$6,'Base de Produtos'!$B$6:$B$36,0),2),0)-$F$7-$F$11-$E18)<=0,"—",CEILING($C$19/(1-IFERROR(INDEX('Base de Produtos'!$B$6:$H$36,MATCH($C$6,'Base de Produtos'!$B$6:$B$36,0),2),0)-$F$7-$F$11-$E18)+0.1,1)-0.1)) -> 75.9 | G18: =IF(ISNUMBER(F18),F18*(1-IFERROR(INDEX('Base de Produtos'!$B$6:$H$36,MATCH($C$6,'Base de Produtos'!$B$6:$B$36,0),2),0)-$F$7-$F$11)-$C$19,"") -> 7.961 | H18: =IF(OR($C$8="",$E18=""),"",IF((1-IFERROR(INDEX('Base de Produtos'!$B$6:$H$36,MATCH($C$6,'Base de Produtos'!$B$6:$B$36,0),3),0)-$F$7-$F$11-$E18)<=0,"—",CEILING($C$19/(1-IFERROR(INDEX('Base de Produtos'!$B$6:$H$36,MATCH($C$6,'Base de Produtos'!$B$6:$B$36,0),3),0)-$F$7-$F$11-$E18)+0.1,1)-0.1)) -> 81.9 | I18: =IF(ISNUMBER(H18),H18*(1-IFERROR(INDEX('Base de Produtos'!$B$6:$H$36,MATCH($C$6,'Base de Produtos'!$B$6:$B$36,0),3),0)-$F$7-$F$11)-$C$19,"") -> 8.606
B19: CUSTO TOTAL POR UNIDADE | C19: =SUM(C16:C18) -> 52 | E19: ='Base de Produtos'!J13 -> 0.15 | F19: =IF(OR($C$8="",$E19=""),"",IF((1-IFERROR(INDEX('Base de Produtos'!$B$6:$H$36,MATCH($C$6,'Base de Produtos'!$B$6:$B$36,0),2),0)-$F$7-$F$11-$E19)<=0,"—",CEILING($C$19/(1-IFERROR(INDEX('Base de Produtos'!$B$6:$H$36,MATCH($C$6,'Base de Produtos'!$B$6:$B$36,0),2),0)-$F$7-$F$11-$E19)+0.1,1)-0.1)) -> 81.9 | G19: =IF(ISNUMBER(F19),F19*(1-IFERROR(INDEX('Base de Produtos'!$B$6:$H$36,MATCH($C$6,'Base de Produtos'!$B$6:$B$36,0),2),0)-$F$7-$F$11)-$C$19,"") -> 12.701 | H19: =IF(OR($C$8="",$E19=""),"",IF((1-IFERROR(INDEX('Base de Produtos'!$B$6:$H$36,MATCH($C$6,'Base de Produtos'!$B$6:$B$36,0),3),0)-$F$7-$F$11-$E19)<=0,"—",CEILING($C$19/(1-IFERROR(INDEX('Base de Produtos'!$B$6:$H$36,MATCH($C$6,'Base de Produtos'!$B$6:$B$36,0),3),0)-$F$7-$F$11-$E19)+0.1,1)-0.1)) -> 88.9 | I19: =IF(ISNUMBER(H19),H19*(1-IFERROR(INDEX('Base de Produtos'!$B$6:$H$36,MATCH($C$6,'Base de Produtos'!$B$6:$B$36,0),3),0)-$F$7-$F$11)-$C$19,"") -> 13.786
E20: ='Base de Produtos'!J14 -> 0.2 | F20: =IF(OR($C$8="",$E20=""),"",IF((1-IFERROR(INDEX('Base de Produtos'!$B$6:$H$36,MATCH($C$6,'Base de Produtos'!$B$6:$B$36,0),2),0)-$F$7-$F$11-$E20)<=0,"—",CEILING($C$19/(1-IFERROR(INDEX('Base de Produtos'!$B$6:$H$36,MATCH($C$6,'Base de Produtos'!$B$6:$B$36,0),2),0)-$F$7-$F$11-$E20)+0.1,1)-0.1)) -> 88.9 | G20: =IF(ISNUMBER(F20),F20*(1-IFERROR(INDEX('Base de Produtos'!$B$6:$H$36,MATCH($C$6,'Base de Produtos'!$B$6:$B$36,0),2),0)-$F$7-$F$11)-$C$19,"") -> 18.231 | H20: =IF(OR($C$8="",$E20=""),"",IF((1-IFERROR(INDEX('Base de Produtos'!$B$6:$H$36,MATCH($C$6,'Base de Produtos'!$B$6:$B$36,0),3),0)-$F$7-$F$11-$E20)<=0,"—",CEILING($C$19/(1-IFERROR(INDEX('Base de Produtos'!$B$6:$H$36,MATCH($C$6,'Base de Produtos'!$B$6:$B$36,0),3),0)-$F$7-$F$11-$E20)+0.1,1)-0.1)) -> 96.9 | I20: =IF(ISNUMBER(H20),H20*(1-IFERROR(INDEX('Base de Produtos'!$B$6:$H$36,MATCH($C$6,'Base de Produtos'!$B$6:$B$36,0),3),0)-$F$7-$F$11)-$C$19,"") -> 19.706
B21: ④ Preço sugerido | E21: ='Base de Produtos'!J15 -> 0.25 | F21: =IF(OR($C$8="",$E21=""),"",IF((1-IFERROR(INDEX('Base de Produtos'!$B$6:$H$36,MATCH($C$6,'Base de Produtos'!$B$6:$B$36,0),2),0)-$F$7-$F$11-$E21)<=0,"—",CEILING($C$19/(1-IFERROR(INDEX('Base de Produtos'!$B$6:$H$36,MATCH($C$6,'Base de Produtos'!$B$6:$B$36,0),2),0)-$F$7-$F$11-$E21)+0.1,1)-0.1)) -> 96.9 | G21: =IF(ISNUMBER(F21),F21*(1-IFERROR(INDEX('Base de Produtos'!$B$6:$H$36,MATCH($C$6,'Base de Produtos'!$B$6:$B$36,0),2),0)-$F$7-$F$11)-$C$19,"") -> 24.551 | H21: =IF(OR($C$8="",$E21=""),"",IF((1-IFERROR(INDEX('Base de Produtos'!$B$6:$H$36,MATCH($C$6,'Base de Produtos'!$B$6:$B$36,0),3),0)-$F$7-$F$11-$E21)<=0,"—",CEILING($C$19/(1-IFERROR(INDEX('Base de Produtos'!$B$6:$H$36,MATCH($C$6,'Base de Produtos'!$B$6:$B$36,0),3),0)-$F$7-$F$11-$E21)+0.1,1)-0.1)) -> 106.9 | I21: =IF(ISNUMBER(H21),H21*(1-IFERROR(INDEX('Base de Produtos'!$B$6:$H$36,MATCH($C$6,'Base de Produtos'!$B$6:$B$36,0),3),0)-$F$7-$F$11)-$C$19,"") -> 27.106
B22: PREÇO DE VENDA | C22: =IF($C$8="","",IF((1-$F$6-$F$7-$F$11-$C$10)<=0,"Lucro alto demais",CEILING($C$19/(1-$F$6-$F$7-$F$11-$C$10)+0.1,1)-0.1)) -> 88.9 | E22: ='Base de Produtos'!J16 -> 0.3 | F22: =IF(OR($C$8="",$E22=""),"",IF((1-IFERROR(INDEX('Base de Produtos'!$B$6:$H$36,MATCH($C$6,'Base de Produtos'!$B$6:$B$36,0),2),0)-$F$7-$F$11-$E22)<=0,"—",CEILING($C$19/(1-IFERROR(INDEX('Base de Produtos'!$B$6:$H$36,MATCH($C$6,'Base de Produtos'!$B$6:$B$36,0),2),0)-$F$7-$F$11-$E22)+0.1,1)-0.1)) -> 106.9 | G22: =IF(ISNUMBER(F22),F22*(1-IFERROR(INDEX('Base de Produtos'!$B$6:$H$36,MATCH($C$6,'Base de Produtos'!$B$6:$B$36,0),2),0)-$F$7-$F$11)-$C$19,"") -> 32.451 | H22: =IF(OR($C$8="",$E22=""),"",IF((1-IFERROR(INDEX('Base de Produtos'!$B$6:$H$36,MATCH($C$6,'Base de Produtos'!$B$6:$B$36,0),3),0)-$F$7-$F$11-$E22)<=0,"—",CEILING($C$19/(1-IFERROR(INDEX('Base de Produtos'!$B$6:$H$36,MATCH($C$6,'Base de Produtos'!$B$6:$B$36,0),3),0)-$F$7-$F$11-$E22)+0.1,1)-0.1)) -> 118.9 | I22: =IF(ISNUMBER(H22),H22*(1-IFERROR(INDEX('Base de Produtos'!$B$6:$H$36,MATCH($C$6,'Base de Produtos'!$B$6:$B$36,0),3),0)-$F$7-$F$11)-$C$19,"") -> 35.986
B23: Lucro por venda | C23: =IF(ISNUMBER($C$22),$C$22*(1-$F$6-$F$7-$F$11)-$C$19,"") -> 18.231 | E23: ='Base de Produtos'!J17 -> 0.35 | F23: =IF(OR($C$8="",$E23=""),"",IF((1-IFERROR(INDEX('Base de Produtos'!$B$6:$H$36,MATCH($C$6,'Base de Produtos'!$B$6:$B$36,0),2),0)-$F$7-$F$11-$E23)<=0,"—",CEILING($C$19/(1-IFERROR(INDEX('Base de Produtos'!$B$6:$H$36,MATCH($C$6,'Base de Produtos'!$B$6:$B$36,0),2),0)-$F$7-$F$11-$E23)+0.1,1)-0.1)) -> 118.9 | G23: =IF(ISNUMBER(F23),F23*(1-IFERROR(INDEX('Base de Produtos'!$B$6:$H$36,MATCH($C$6,'Base de Produtos'!$B$6:$B$36,0),2),0)-$F$7-$F$11)-$C$19,"") -> 41.931 | H23: =IF(OR($C$8="",$E23=""),"",IF((1-IFERROR(INDEX('Base de Produtos'!$B$6:$H$36,MATCH($C$6,'Base de Produtos'!$B$6:$B$36,0),3),0)-$F$7-$F$11-$E23)<=0,"—",CEILING($C$19/(1-IFERROR(INDEX('Base de Produtos'!$B$6:$H$36,MATCH($C$6,'Base de Produtos'!$B$6:$B$36,0),3),0)-$F$7-$F$11-$E23)+0.1,1)-0.1)) -> 133.9 | I23: =IF(ISNUMBER(H23),H23*(1-IFERROR(INDEX('Base de Produtos'!$B$6:$H$36,MATCH($C$6,'Base de Produtos'!$B$6:$B$36,0),3),0)-$F$7-$F$11)-$C$19,"") -> 47.086
B24: Margem de lucro real | C24: =IF(ISNUMBER($C$22),C23/$C$22,"") -> 0.20507312 | E24: ='Base de Produtos'!J18 -> 0.4 | F24: =IF(OR($C$8="",$E24=""),"",IF((1-IFERROR(INDEX('Base de Produtos'!$B$6:$H$36,MATCH($C$6,'Base de Produtos'!$B$6:$B$36,0),2),0)-$F$7-$F$11-$E24)<=0,"—",CEILING($C$19/(1-IFERROR(INDEX('Base de Produtos'!$B$6:$H$36,MATCH($C$6,'Base de Produtos'!$B$6:$B$36,0),2),0)-$F$7-$F$11-$E24)+0.1,1)-0.1)) -> 133.9 | G24: =IF(ISNUMBER(F24),F24*(1-IFERROR(INDEX('Base de Produtos'!$B$6:$H$36,MATCH($C$6,'Base de Produtos'!$B$6:$B$36,0),2),0)-$F$7-$F$11)-$C$19,"") -> 53.781 | H24: =IF(OR($C$8="",$E24=""),"",IF((1-IFERROR(INDEX('Base de Produtos'!$B$6:$H$36,MATCH($C$6,'Base de Produtos'!$B$6:$B$36,0),3),0)-$F$7-$F$11-$E24)<=0,"—",CEILING($C$19/(1-IFERROR(INDEX('Base de Produtos'!$B$6:$H$36,MATCH($C$6,'Base de Produtos'!$B$6:$B$36,0),3),0)-$F$7-$F$11-$E24)+0.1,1)-0.1)) -> 153.9 | I24: =IF(ISNUMBER(H24),H24*(1-IFERROR(INDEX('Base de Produtos'!$B$6:$H$36,MATCH($C$6,'Base de Produtos'!$B$6:$B$36,0),3),0)-$F$7-$F$11)-$C$19,"") -> 61.886
B25: Mercado Livre cobra (tarifa) | C25: =IF(ISNUMBER($C$22),$C$22*$F$6,"") -> 11.557 | E25: ='Base de Produtos'!J19 -> 0.5 | F25: =IF(OR($C$8="",$E25=""),"",IF((1-IFERROR(INDEX('Base de Produtos'!$B$6:$H$36,MATCH($C$6,'Base de Produtos'!$B$6:$B$36,0),2),0)-$F$7-$F$11-$E25)<=0,"—",CEILING($C$19/(1-IFERROR(INDEX('Base de Produtos'!$B$6:$H$36,MATCH($C$6,'Base de Produtos'!$B$6:$B$36,0),2),0)-$F$7-$F$11-$E25)+0.1,1)-0.1)) -> 179.9 | G25: =IF(ISNUMBER(F25),F25*(1-IFERROR(INDEX('Base de Produtos'!$B$6:$H$36,MATCH($C$6,'Base de Produtos'!$B$6:$B$36,0),2),0)-$F$7-$F$11)-$C$19,"") -> 90.121 | H25: =IF(OR($C$8="",$E25=""),"",IF((1-IFERROR(INDEX('Base de Produtos'!$B$6:$H$36,MATCH($C$6,'Base de Produtos'!$B$6:$B$36,0),3),0)-$F$7-$F$11-$E25)<=0,"—",CEILING($C$19/(1-IFERROR(INDEX('Base de Produtos'!$B$6:$H$36,MATCH($C$6,'Base de Produtos'!$B$6:$B$36,0),3),0)-$F$7-$F$11-$E25)+0.1,1)-0.1)) -> 216.9 | I25: =IF(ISNUMBER(H25),H25*(1-IFERROR(INDEX('Base de Produtos'!$B$6:$H$36,MATCH($C$6,'Base de Produtos'!$B$6:$B$36,0),3),0)-$F$7-$F$11)-$C$19,"") -> 108.506
B26: Imposto sobre a venda | C26: =IF(ISNUMBER($C$22),$C$22*$F$7,"") -> 5.334 | E26: ='Base de Produtos'!J20 -> 0.6 | F26: =IF(OR($C$8="",$E26=""),"",IF((1-IFERROR(INDEX('Base de Produtos'!$B$6:$H$36,MATCH($C$6,'Base de Produtos'!$B$6:$B$36,0),2),0)-$F$7-$F$11-$E26)<=0,"—",CEILING($C$19/(1-IFERROR(INDEX('Base de Produtos'!$B$6:$H$36,MATCH($C$6,'Base de Produtos'!$B$6:$B$36,0),2),0)-$F$7-$F$11-$E26)+0.1,1)-0.1)) -> 273.9 | G26: =IF(ISNUMBER(F26),F26*(1-IFERROR(INDEX('Base de Produtos'!$B$6:$H$36,MATCH($C$6,'Base de Produtos'!$B$6:$B$36,0),2),0)-$F$7-$F$11)-$C$19,"") -> 164.381 | H26: =IF(OR($C$8="",$E26=""),"",IF((1-IFERROR(INDEX('Base de Produtos'!$B$6:$H$36,MATCH($C$6,'Base de Produtos'!$B$6:$B$36,0),3),0)-$F$7-$F$11-$E26)<=0,"—",CEILING($C$19/(1-IFERROR(INDEX('Base de Produtos'!$B$6:$H$36,MATCH($C$6,'Base de Produtos'!$B$6:$B$36,0),3),0)-$F$7-$F$11-$E26)+0.1,1)-0.1)) -> 371.9 | I26: =IF(ISNUMBER(H26),H26*(1-IFERROR(INDEX('Base de Produtos'!$B$6:$H$36,MATCH($C$6,'Base de Produtos'!$B$6:$B$36,0),3),0)-$F$7-$F$11)-$C$19,"") -> 223.206
B27: Ads + devoluções | C27: =IF(ISNUMBER($C$22),$C$22*$F$11,"") -> 1.778 | E27: A linha verde é o lucro que você escolheu. Premium = parcelamento em 12x sem juros e tarifa maior.
B28: =IF(AND(ISNUMBER($C$22),$C$22<79),"Abaixo de R$ 79: se usar Flex ou envio próprio, o ML cobra custo fixo (~R$ 6,25 a R$ 6,75). Some no frete de envio.","")

Sheet Base de Produtos
B2: Base de Produtos
B3: Edite os valores amarelos. A Calculadora puxa tudo daqui pelo tipo de produto.
B5: Tipo de produto | C5: Tarifa ML Clássico | D5: Tarifa ML Premium | E5: Imposto sobre a venda | F5: Imposto de importação | G5: ICMS importação | H5: Embalagem (R$ por unidade) | J5: Configurações gerais
B6: Acessórios para Veículos | C6: 0.12 | D6: 0.17 | E6: 0.06 | F6: 0.3 | G6: 0.2 | H6: 2 | J6: Mercado Ads (% das vendas) | K6: 0
B7: Agro | C7: 0.115 | D7: 0.165 | E7: 0.06 | F7: 0.3 | G7: 0.2 | H7: 2 | J7: Devoluções / perdas (%) | K7: 0.02
B8: Alimentos e Bebidas | C8: 0.14 | D8: 0.19 | E8: 0.06 | F8: 0.3 | G8: 0.2 | H8: 2 | J8: Use 0% em Ads se não anuncia no Mercado Ads.
B9: Antiguidades e Coleções | C9: 0.115 | D9: 0.165 | E9: 0.06 | F9: 0.3 | G9: 0.2 | H9: 2
B10: Arte, Papelaria e Armarinho | C10: 0.115 | D10: 0.165 | E10: 0.06 | F10: 0.3 | G10: 0.2 | H10: 2 | J10: Opções de lucro
B11: Bebês | C11: 0.14 | D11: 0.19 | E11: 0.06 | F11: 0.3 | G11: 0.2 | H11: 2 | J11: 0.05
B12: Beleza e Cuidado Pessoal | C12: 0.14 | D12: 0.19 | E12: 0.06 | F12: 0.3 | G12: 0.2 | H12: 2 | J12: 0.1
B13: Brinquedos e Hobbies | C13: 0.115 | D13: 0.165 | E13: 0.06 | F13: 0.3 | G13: 0.2 | H13: 2 | J13: 0.15
B14: Calçados, Roupas e Bolsas | C14: 0.14 | D14: 0.19 | E14: 0.06 | F14: 0.3 | G14: 0.2 | H14: 2 | J14: 0.2
B15: Câmeras e Acessórios | C15: 0.11 | D15: 0.16 | E15: 0.06 | F15: 0.3 | G15: 0.2 | H15: 2 | J15: 0.25
B16: Casa, Móveis e Decoração | C16: 0.115 | D16: 0.165 | E16: 0.06 | F16: 0.3 | G16: 0.2 | H16: 2 | J16: 0.3
B17: Celulares e Telefones | C17: 0.11 | D17: 0.16 | E17: 0.06 | F17: 0.3 | G17: 0.2 | H17: 2 | J17: 0.35
B18: Construção | C18: 0.115 | D18: 0.165 | E18: 0.06 | F18: 0.3 | G18: 0.2 | H18: 2 | J18: 0.4
B19: Eletrodomésticos | C19: 0.11 | D19: 0.16 | E19: 0.06 | F19: 0.3 | G19: 0.2 | H19: 2 | J19: 0.5
B20: Eletrônicos, Áudio e Vídeo | C20: 0.13 | D20: 0.18 | E20: 0.06 | F20: 0.3 | G20: 0.2 | H20: 2 | J20: 0.6
B21: Esportes e Fitness | C21: 0.14 | D21: 0.19 | E21: 0.06 | F21: 0.3 | G21: 0.2 | H21: 2 | J21: Altere para as margens que você usa.
B22: Festas e Lembrancinhas | C22: 0.115 | D22: 0.165 | E22: 0.06 | F22: 0.3 | G22: 0.2 | H22: 2
B23: Games | C23: 0.13 | D23: 0.18 | E23: 0.06 | F23: 0.3 | G23: 0.2 | H23: 2
B24: Indústria e Comércio | C24: 0.12 | D24: 0.17 | E24: 0.06 | F24: 0.3 | G24: 0.2 | H24: 2
B25: Informática | C25: 0.11 | D25: 0.16 | E25: 0.06 | F25: 0.3 | G25: 0.2 | H25: 2
B26: Instrumentos Musicais | C26: 0.115 | D26: 0.165 | E26: 0.06 | F26: 0.3 | G26: 0.2 | H26: 2
B27: Joias e Relógios | C27: 0.125 | D27: 0.175 | E27: 0.06 | F27: 0.3 | G27: 0.2 | H27: 2
B28: Livros, Revistas e Comics | C28: 0.12 | D28: 0.17 | E28: 0.06 | F28: 0.3 | G28: 0.2 | H28: 2
B29: Música, Filmes e Seriados | C29: 0.12 | D29: 0.17 | E29: 0.06 | F29: 0.3 | G29: 0.2 | H29: 2
B30: Pet Shop | C30: 0.125 | D30: 0.175 | E30: 0.06 | F30: 0.3 | G30: 0.2 | H30: 2
B31: Saúde | C31: 0.12 | D31: 0.17 | E31: 0.06 | F31: 0.3 | G31: 0.2 | H31: 2
B37: Linhas em branco acima: cadastre seus próprios tipos de produto.
B39: Fontes e observações
B40: • Tarifa ML: média de cada categoria, conferida em 13/10/2026 (priceva.com/pt/calculadora-taxas-mercado-livre). A tarifa exata da sua subcategoria aparece no Simulador de Custos do Mercado Livre.
B41: • Imposto sobre a venda: 6% é um valor de exemplo (Simples Nacional). Coloque a alíquota que seu contador indicar para cada tipo de produto.
B42: • Imposto de importação e ICMS só são usados quando a origem é Internacional. 30% e 20% são valores de referência para compras via Remessa Conforme acima de US$ 50 (compras até US$ 50 têm imposto federal zerado desde 13/05/2026). Ajuste conforme sua forma de importar.
